[
  {
    "id": "013bc639-0e65-4381-a3dc-c0e114d7fcd3",
    "data": [
      {
        "text": "Holiwis",
        "userDefined": false
      }
    ],
    "isTemplate": false,
    "count": 0,
    "lang": "es",
    "updated": 0
  },
  {
    "id": "5dbb2486-451a-4e0d-9ddf-5525227f0888",
    "data": [
      {
        "text": "Holi, necesito pedirte algo",
        "userDefined": false
      }
    ],
    "isTemplate": false,
    "count": 0,
    "lang": "es",
    "updated": 0
  },
  {
    "id": "9be06ed0-d867-43cc-8947-3ee410add039",
    "data": [
      {
        "text": "Buenas, tengo una duda",
        "userDefined": false
      }
    ],
    "isTemplate": false,
    "count": 0,
    "lang": "es",
    "updated": 0
  },
  {
    "id": "2cc785c3-5fc4-4e94-bfea-1f748432d5b7",
    "data": [
      {
        "text": "Hola, ¿me puedes ayudar?",
        "userDefined": false
      }
    ],
    "isTemplate": false,
    "count": 0,
    "lang": "es",
    "updated": 0
  },
  {
    "id": "65c9c1e7-d933-4e30-9ec5-2311b7b2119f",
    "data": [
      {
        "text": "¿Qué hay de nuevo?",
        "userDefined": false
      }
    ],
    "isTemplate": false,
    "count": 0,
    "lang": "es",
    "updated": 0
  },
  {
    "id": "495a78a4-baf6-45e4-b5ee-c7c473d6e345",
    "data": [
      {
        "text": "¿Cómo andas?",
        "userDefined": false
      }
    ],
    "isTemplate": false,
    "count": 0,
    "lang": "es",
    "updated": 0
  },
  {
    "id": "36cb4da8-3e18-4949-a3ce-6af21f2c39a6",
    "data": [
      {
        "text": "Holiiiii",
        "userDefined": false
      }
    ],
    "isTemplate": false,
    "count": 0,
    "lang": "es",
    "updated": 0
  },
  {
    "id": "ead1ae47-2a1c-4693-afdd-75a418252b4a",
    "data": [
      {
        "text": "Buenos días",
        "userDefined": false
      }
    ],
    "isTemplate": false,
    "count": 0,
    "lang": "es",
    "updated": 0
  },
  {
    "id": "452e77b9-1331-4f7b-a434-4009577781a1",
    "data": [
      {
        "text": "Buenas tardes",
        "userDefined": false
      }
    ],
    "isTemplate": false,
    "count": 0,
    "lang": "es",
    "updated": 0
  },
  {
    "id": "fb6bf3a2-d8bf-41b7-a7b5-75282a0efeff",
    "data": [
      {
        "text": "Hey",
        "userDefined": false
      }
    ],
    "isTemplate": false,
    "count": 0,
    "lang": "es",
    "updated": 0
  },
  {
    "id": "b713a29c-5f76-48f2-8e27-02450356b80b",
    "data": [
      {
        "text": "Hola",
        "userDefined": false
      }
    ],
    "isTemplate": false,
    "count": 0,
    "lang": "es",
    "updated": 0
  }
]