[
  {
    "id": "dd4dabaf-5f03-4a09-9b9d-786c49de98f8",
    "data": [
      {
        "text": "¡Un placer hablar contigo!",
        "userDefined": false
      }
    ],
    "isTemplate": false,
    "count": 0,
    "lang": "es",
    "updated": 0
  },
  {
    "id": "8ed0e445-a0d7-4790-9622-d14ef1632caf",
    "data": [
      {
        "text": "¡Genial, eso era todo, gracias!",
        "userDefined": false
      }
    ],
    "isTemplate": false,
    "count": 0,
    "lang": "es",
    "updated": 0
  },
  {
    "id": "7cba66a9-9659-45ea-b5ca-6bd160dc6cdf",
    "data": [
      {
        "text": "Me ha quedado claro, hasta otra!",
        "userDefined": false
      }
    ],
    "isTemplate": false,
    "count": 0,
    "lang": "es",
    "updated": 0
  },
  {
    "id": "725fee13-d565-4046-a368-58ce3f0627b8",
    "data": [
      {
        "text": "Buenas noches",
        "userDefined": false
      }
    ],
    "isTemplate": false,
    "count": 0,
    "lang": "es",
    "updated": 0
  },
  {
    "id": "2ad7132a-c10d-4ea1-9d57-5f068022c453",
    "data": [
      {
        "text": "Bye",
        "userDefined": false
      }
    ],
    "isTemplate": false,
    "count": 0,
    "lang": "es",
    "updated": 0
  },
  {
    "id": "fbddf27b-b714-48c6-97fd-1d9cd92c5cd7",
    "data": [
      {
        "text": "Me piro vampiro",
        "userDefined": false
      }
    ],
    "isTemplate": false,
    "count": 0,
    "lang": "es",
    "updated": 0
  },
  {
    "id": "c76b028c-96af-43b5-9bcf-39522f9facfd",
    "data": [
      {
        "text": "Nos vemos",
        "userDefined": false
      }
    ],
    "isTemplate": false,
    "count": 0,
    "lang": "es",
    "updated": 0
  },
  {
    "id": "798eb8f8-f994-4634-b5d6-399f4fc37a4b",
    "data": [
      {
        "text": "Cuídate",
        "userDefined": false
      }
    ],
    "isTemplate": false,
    "count": 0,
    "lang": "es",
    "updated": 0
  },
  {
    "id": "bfc92b73-6e31-4612-b161-b33f39da2fca",
    "data": [
      {
        "text": "¡Que tengas un buen día!",
        "userDefined": false
      }
    ],
    "isTemplate": false,
    "count": 0,
    "lang": "es",
    "updated": 0
  },
  {
    "id": "fceb13ab-6816-4736-ab34-3a8e8894eb70",
    "data": [
      {
        "text": "Chao",
        "userDefined": false
      }
    ],
    "isTemplate": false,
    "count": 0,
    "lang": "es",
    "updated": 0
  },
  {
    "id": "c63a7ae6-24b6-49dc-858d-efef0d4295f1",
    "data": [
      {
        "text": "Hasta luego",
        "userDefined": false
      }
    ],
    "isTemplate": false,
    "count": 0,
    "lang": "es",
    "updated": 0
  },
  {
    "id": "03b0a976-b21f-43d2-bfc5-34878b30724f",
    "data": [
      {
        "text": "Adiós",
        "userDefined": false
      }
    ],
    "isTemplate": false,
    "count": 0,
    "lang": "es",
    "updated": 0
  },
  {
    "id": "3e5312d8-a262-431d-aaa9-1d1332e61412",
    "data": [
      {
        "text": "Me voy, gracias.",
        "userDefined": false
      }
    ],
    "isTemplate": false,
    "count": 0,
    "lang": "es",
    "updated": 0
  }
]